notion_blockify/__init__.py
notion_blockify/blocks.py
notion_blockify/convert.py
notion_blockify/replace.py
notion_blockify-0.1.1.dist-info/LICENSE
notion_blockify-0.1.1.dist-info/METADATA
notion_blockify-0.1.1.dist-info/WHEEL
notion_blockify-0.1.1.dist-info/top_level.txt
notion_blockify-0.1.1.dist-info/RECORD
