Metadata-Version: 2.1
Name: notion-blockify
Version: 0.1.1
Summary: Convert Markdown to Notion blocks
Author-email: Minseong Kim <emeraldgoose@gmail.com>
License: MIT License
Project-URL: Homepage, https://github.com/emeraldgoose/notion-blockify
Keywords: notion,markdown,converter,blocks
Requires-Python: >=3.8
License-File: LICENSE
